{"nodes": [{"id": "users_zibby_workspace_zibby_2_0_design_task_card_jsx", "label": "task-card.jsx", "file_type": "code", "source_file": "/Users/zibby/Workspace/Zibby-2.0/design/task-card.jsx", "source_location": "L1"}, {"id": "task_card_taskcard", "label": "TaskCard()", "file_type": "code", "source_file": "/Users/zibby/Workspace/Zibby-2.0/design/task-card.jsx", "source_location": "L7"}, {"id": "task_card_column", "label": "Column()", "file_type": "code", "source_file": "/Users/zibby/Workspace/Zibby-2.0/design/task-card.jsx", "source_location": "L115"}], "edges": [{"source": "users_zibby_workspace_zibby_2_0_design_task_card_jsx", "target": "task_card_taskcard", "relation": "contains", "confidence": "EXTRACTED", "source_file": "/Users/zibby/Workspace/Zibby-2.0/design/task-card.jsx", "source_location": "L7", "weight": 1.0}, {"source": "users_zibby_workspace_zibby_2_0_design_task_card_jsx", "target": "task_card_column", "relation": "contains", "confidence": "EXTRACTED", "source_file": "/Users/zibby/Workspace/Zibby-2.0/design/task-card.jsx", "source_location": "L115", "weight": 1.0}], "raw_calls": [{"caller_nid": "task_card_taskcard", "callee": "replace", "source_file": "/Users/zibby/Workspace/Zibby-2.0/design/task-card.jsx", "source_location": "L62"}, {"caller_nid": "task_card_taskcard", "callee": "pop", "source_file": "/Users/zibby/Workspace/Zibby-2.0/design/task-card.jsx", "source_location": "L63"}, {"caller_nid": "task_card_taskcard", "callee": "split", "source_file": "/Users/zibby/Workspace/Zibby-2.0/design/task-card.jsx", "source_location": "L63"}, {"caller_nid": "task_card_taskcard", "callee": "join", "source_file": "/Users/zibby/Workspace/Zibby-2.0/design/task-card.jsx", "source_location": "L65"}, {"caller_nid": "task_card_taskcard", "callee": "fmtDuration", "source_file": "/Users/zibby/Workspace/Zibby-2.0/design/task-card.jsx", "source_location": "L74"}, {"caller_nid": "task_card_taskcard", "callee": "fmtDuration", "source_file": "/Users/zibby/Workspace/Zibby-2.0/design/task-card.jsx", "source_location": "L79"}, {"caller_nid": "task_card_taskcard", "callee": "fmtDuration", "source_file": "/Users/zibby/Workspace/Zibby-2.0/design/task-card.jsx", "source_location": "L84"}, {"caller_nid": "task_card_taskcard", "callee": "toFixed", "source_file": "/Users/zibby/Workspace/Zibby-2.0/design/task-card.jsx", "source_location": "L89"}, {"caller_nid": "task_card_taskcard", "callee": "toFixed", "source_file": "/Users/zibby/Workspace/Zibby-2.0/design/task-card.jsx", "source_location": "L89"}, {"caller_nid": "task_card_column", "callee": "tdS", "source_file": "/Users/zibby/Workspace/Zibby-2.0/design/task-card.jsx", "source_location": "L116"}]}