{"nodes": [{"id": "apps_desktop_src_main_index_ts", "label": "index.ts", "file_type": "code", "source_file": "apps/desktop/src/main/index.ts", "source_location": "L1"}, {"id": "index_isgitrepo", "label": "isGitRepo()", "file_type": "code", "source_file": "apps/desktop/src/main/index.ts", "source_location": "L30"}, {"id": "index_hasgitorigin", "label": "hasGitOrigin()", "file_type": "code", "source_file": "apps/desktop/src/main/index.ts", "source_location": "L39"}, {"id": "index_emittorenderer", "label": "emitToRenderer()", "file_type": "code", "source_file": "apps/desktop/src/main/index.ts", "source_location": "L48"}, {"id": "index_registeripc", "label": "registerIpc()", "file_type": "code", "source_file": "apps/desktop/src/main/index.ts", "source_location": "L52"}, {"id": "index_createwindow", "label": "createWindow()", "file_type": "code", "source_file": "apps/desktop/src/main/index.ts", "source_location": "L166"}], "edges": [{"source": "apps_desktop_src_main_index_ts", "target": "electron", "relation": "imports_from", "confidence": "EXTRACTED", "source_file": "apps/desktop/src/main/index.ts", "source_location": "L1", "weight": 1.0}, {"source": "apps_desktop_src_main_index_ts", "target": "node_path", "relation": "imports_from", "confidence": "EXTRACTED", "source_file": "apps/desktop/src/main/index.ts", "source_location": "L2", "weight": 1.0}, {"source": "apps_desktop_src_main_index_ts", "target": "promises", "relation": "imports_from", "confidence": "EXTRACTED", "source_file": "apps/desktop/src/main/index.ts", "source_location": "L3", "weight": 1.0}, {"source": "apps_desktop_src_main_index_ts", "target": "node_child_process", "relation": "imports_from", "confidence": "EXTRACTED", "source_file": "apps/desktop/src/main/index.ts", "source_location": "L4", "weight": 1.0}, {"source": "apps_desktop_src_main_index_ts", "target": "node_util", "relation": "imports_from", "confidence": "EXTRACTED", "source_file": "apps/desktop/src/main/index.ts", "source_location": "L5", "weight": 1.0}, {"source": "apps_desktop_src_main_index_ts", "target": "ipc", "relation": "imports_from", "confidence": "EXTRACTED", "source_file": "apps/desktop/src/main/index.ts", "source_location": "L6", "weight": 1.0}, {"source": "apps_desktop_src_main_index_ts", "target": "ai_refiner", "relation": "imports_from", "confidence": "EXTRACTED", "source_file": "apps/desktop/src/main/index.ts", "source_location": "L20", "weight": 1.0}, {"source": "apps_desktop_src_main_index_ts", "target": "orchestrator", "relation": "imports_from", "confidence": "EXTRACTED", "source_file": "apps/desktop/src/main/index.ts", "source_location": "L21", "weight": 1.0}, {"source": "apps_desktop_src_main_index_ts", "target": "apps_desktop_src_main_state_store", "relation": "imports_from", "confidence": "EXTRACTED", "source_file": "apps/desktop/src/main/index.ts", "source_location": "L22", "weight": 1.0}, {"source": "apps_desktop_src_main_index_ts", "target": "index_isgitrepo", "relation": "contains", "confidence": "EXTRACTED", "source_file": "apps/desktop/src/main/index.ts", "source_location": "L30", "weight": 1.0}, {"source": "apps_desktop_src_main_index_ts", "target": "index_hasgitorigin", "relation": "contains", "confidence": "EXTRACTED", "source_file": "apps/desktop/src/main/index.ts", "source_location": "L39", "weight": 1.0}, {"source": "apps_desktop_src_main_index_ts", "target": "index_emittorenderer", "relation": "contains", "confidence": "EXTRACTED", "source_file": "apps/desktop/src/main/index.ts", "source_location": "L48", "weight": 1.0}, {"source": "apps_desktop_src_main_index_ts", "target": "index_registeripc", "relation": "contains", "confidence": "EXTRACTED", "source_file": "apps/desktop/src/main/index.ts", "source_location": "L52", "weight": 1.0}, {"source": "apps_desktop_src_main_index_ts", "target": "index_createwindow", "relation": "contains", "confidence": "EXTRACTED", "source_file": "apps/desktop/src/main/index.ts", "source_location": "L166", "weight": 1.0}], "raw_calls": [{"caller_nid": "index_isgitrepo", "callee": "access", "source_file": "apps/desktop/src/main/index.ts", "source_location": "L32"}, {"caller_nid": "index_isgitrepo", "callee": "join", "source_file": "apps/desktop/src/main/index.ts", "source_location": "L32"}, {"caller_nid": "index_hasgitorigin", "callee": "execFileP", "source_file": "apps/desktop/src/main/index.ts", "source_location": "L41"}, {"caller_nid": "index_hasgitorigin", "callee": "trim", "source_file": "apps/desktop/src/main/index.ts", "source_location": "L42"}, {"caller_nid": "index_emittorenderer", "callee": "isDestroyed", "source_file": "apps/desktop/src/main/index.ts", "source_location": "L49"}, {"caller_nid": "index_emittorenderer", "callee": "send", "source_file": "apps/desktop/src/main/index.ts", "source_location": "L49"}, {"caller_nid": "index_registeripc", "callee": "handle", "source_file": "apps/desktop/src/main/index.ts", "source_location": "L53"}, {"caller_nid": "index_registeripc", "callee": "handle", "source_file": "apps/desktop/src/main/index.ts", "source_location": "L65"}, {"caller_nid": "index_registeripc", "callee": "handle", "source_file": "apps/desktop/src/main/index.ts", "source_location": "L77"}, {"caller_nid": "index_registeripc", "callee": "handle", "source_file": "apps/desktop/src/main/index.ts", "source_location": "L89"}, {"caller_nid": "index_registeripc", "callee": "handle", "source_file": "apps/desktop/src/main/index.ts", "source_location": "L139"}, {"caller_nid": "index_registeripc", "callee": "handle", "source_file": "apps/desktop/src/main/index.ts", "source_location": "L143"}, {"caller_nid": "index_registeripc", "callee": "handle", "source_file": "apps/desktop/src/main/index.ts", "source_location": "L159"}, {"caller_nid": "index_createwindow", "callee": "join", "source_file": "apps/desktop/src/main/index.ts", "source_location": "L172"}, {"caller_nid": "index_createwindow", "callee": "loadURL", "source_file": "apps/desktop/src/main/index.ts", "source_location": "L180"}, {"caller_nid": "index_createwindow", "callee": "openDevTools", "source_file": "apps/desktop/src/main/index.ts", "source_location": "L181"}, {"caller_nid": "index_createwindow", "callee": "loadFile", "source_file": "apps/desktop/src/main/index.ts", "source_location": "L183"}, {"caller_nid": "index_createwindow", "callee": "join", "source_file": "apps/desktop/src/main/index.ts", "source_location": "L183"}]}